{
    "fields": [
        {
            "id": "a",
            "label": "States\/Union Territory - Total Dist.in India",
            "type": "string"
        },
        {
            "id": "b",
            "label": "Name of the District",
            "type": "string"
        },
        {
            "id": "c",
            "label": "No.of - SCs",
            "type": "string"
        },
        {
            "id": "d",
            "label": "No.of - PHCs",
            "type": "string"
        },
        {
            "id": "e",
            "label": "No.of - CHCs",
            "type": "string"
        }
    ],
    "data": [
        [
            "A & N Islands ",
            "Andamans",
            "76",
            "16",
            "3"
        ],
        [
            "A & N Islands ",
            "Nicobars",
            "32",
            "4",
            "1"
        ],
        [
            "A & N Islands ",
            "Total",
            "108",
            "20",
            "4"
        ],
        [
            "Andhra Pradesh",
            "Adilabad",
            "570",
            "76",
            "8"
        ],
        [
            "Andhra Pradesh",
            "Anantapur",
            "609",
            "76",
            "11"
        ],
        [
            "Andhra Pradesh",
            "Chittoor",
            "653",
            "91",
            "8"
        ],
        [
            "Andhra Pradesh",
            "Cuddapah",
            "462",
            "68",
            "6"
        ],
        [
            "Andhra Pradesh",
            "East Godavari",
            "809",
            "84",
            "9"
        ],
        [
            "Andhra Pradesh",
            "Guntur",
            "689",
            "72",
            "8"
        ],
        [
            "Andhra Pradesh",
            "Hyderabad",
            "53",
            "0",
            "1"
        ],
        [
            "Andhra Pradesh",
            "Karimnagar",
            "580",
            "72",
            "6"
        ],
        [
            "Andhra Pradesh",
            "Khammam",
            "591",
            "76",
            "5"
        ],
        [
            "Andhra Pradesh",
            "Krishna",
            "609",
            "72",
            "8"
        ],
        [
            "Andhra Pradesh",
            "Kurnool",
            "476",
            "77",
            "7"
        ],
        [
            "Andhra Pradesh",
            "Mahbubnagar",
            "680",
            "86",
            "8"
        ],
        [
            "Andhra Pradesh",
            "Medak",
            "489",
            "66",
            "8"
        ],
        [
            "Andhra Pradesh",
            "Nalgonda",
            "626",
            "72",
            "7"
        ],
        [
            "Andhra Pradesh",
            "Nellore",
            "481",
            "65",
            "6"
        ],
        [
            "Andhra Pradesh",
            "Nizamabad",
            "412",
            "45",
            "4"
        ],
        [
            "Andhra Pradesh",
            "Prakasam",
            "555",
            "81",
            "6"
        ],
        [
            "Andhra Pradesh",
            "Rangareddi",
            "399",
            "41",
            "10"
        ],
        [
            "Andhra Pradesh",
            "Srikakulam",
            "488",
            "73",
            "10"
        ],
        [
            "Andhra Pradesh",
            "Visakhapatnam",
            "573",
            "82",
            "11"
        ],
        [
            "Andhra Pradesh",
            "Vizianagaram",
            "470",
            "59",
            "7"
        ],
        [
            "Andhra Pradesh",
            "Warangal",
            "605",
            "68",
            "8"
        ],
        [
            "Andhra Pradesh",
            "West Godavari",
            "643",
            "68",
            "5"
        ],
        [
            "Andhra Pradesh",
            "Total",
            "12522",
            "1570",
            "167"
        ],
        [
            "Arunachal Pradesh",
            "Changlang",
            "24",
            "6",
            "2"
        ],
        [
            "Arunachal Pradesh",
            "Dibang Valley",
            "17",
            "5",
            "2"
        ],
        [
            "Arunachal Pradesh",
            "East Kameng",
            "23",
            "6",
            "1"
        ],
        [
            "Arunachal Pradesh",
            "East Siang",
            "20",
            "15",
            "3"
        ],
        [
            "Arunachal Pradesh",
            "Lohit",
            "36",
            "8",
            "3"
        ],
        [
            "Arunachal Pradesh",
            "Lower Subansiri",
            "27",
            "5",
            "1"
        ],
        [
            "Arunachal Pradesh",
            "Papum Pare",
            "35",
            "6",
            "2"
        ],
        [
            "Arunachal Pradesh",
            "Tawang",
            "12",
            "5",
            "0"
        ],
        [
            "Arunachal Pradesh",
            "Tirap",
            "31",
            "4",
            "2"
        ],
        [
            "Arunachal Pradesh",
            "Upper Siang",
            "14",
            "3",
            "2"
        ],
        [
            "Arunachal Pradesh",
            "Upper Subansiri",
            "27",
            "6",
            "1"
        ],
        [
            "Arunachal Pradesh",
            "West Kameng",
            "34",
            "3",
            "3"
        ],
        [
            "Arunachal Pradesh",
            "West Siang",
            "39",
            "9",
            "5"
        ],
        [
            "Arunachal Pradesh",
            "KurumKumey",
            "40",
            "4",
            "4"
        ],
        [
            "Arunachal Pradesh",
            "Total",
            "379",
            "85",
            "31"
        ],
        [
            "Assam",
            "Barpeta",
            "351",
            "41",
            "6"
        ],
        [
            "Assam",
            "Bongaigaon",
            "95",
            "23",
            "4"
        ],
        [
            "Assam",
            "Cachar",
            "288",
            "22",
            "2"
        ],
        [
            "Assam",
            "Darrang",
            "322",
            "35",
            "7"
        ],
        [
            "Assam",
            "Dhemaji",
            "88",
            "9",
            "3"
        ],
        [
            "Assam",
            "Dhubri",
            "303",
            "23",
            "6"
        ],
        [
            "Assam",
            "Dibrugarh",
            "180",
            "37",
            "5"
        ],
        [
            "Assam",
            "Goalpara",
            "192",
            "17",
            "1"
        ],
        [
            "Assam",
            "Golaghat",
            "212",
            "32",
            "5"
        ],
        [
            "Assam",
            "Hailakandi",
            "103",
            "8",
            "1"
        ],
        [
            "Assam",
            "Jorhat",
            "149",
            "24",
            "4"
        ],
        [
            "Assam",
            "Kamrup",
            "338",
            "51",
            "9"
        ],
        [
            "Assam",
            "Karbi Anglong",
            "159",
            "35",
            "5"
        ],
        [
            "Assam",
            "Karimganj",
            "232",
            "16",
            "1"
        ],
        [
            "Assam",
            "Kokrajhar",
            "198",
            "37",
            "3"
        ],
        [
            "Assam",
            "Lakhimpur",
            "183",
            "23",
            "5"
        ],
        [
            "Assam",
            "Marigaon",
            "111",
            "13",
            "2"
        ],
        [
            "Assam",
            "Nagaon",
            "464",
            "38",
            "9"
        ],
        [
            "Assam",
            "Nalbari",
            "280",
            "42",
            "9"
        ],
        [
            "Assam",
            "N.C.HILLS",
            "73",
            "12",
            "2"
        ],
        [
            "Assam",
            "Sibsagar",
            "227",
            "30",
            "2"
        ],
        [
            "Assam",
            "Sonitpur",
            "325",
            "28",
            "5"
        ],
        [
            "Assam",
            "Tinsukia",
            "236",
            "14",
            "4"
        ],
        [
            "Assam",
            "Total",
            "5109",
            "610",
            "100"
        ],
        [
            "Bihar",
            "Araria",
            "200",
            "39",
            "3"
        ],
        [
            "Bihar",
            "Aurangabad",
            "207",
            "69",
            "3"
        ],
        [
            "Bihar",
            "Arwal",
            "46",
            "26",
            "0"
        ],
        [
            "Bihar",
            "Banka",
            "227",
            "34",
            "3"
        ],
        [
            "Bihar",
            "Begusarai",
            "288",
            "42",
            "2"
        ],
        [
            "Bihar",
            "Bhagalpur",
            "280",
            "57",
            "2"
        ],
        [
            "Bihar",
            "Bhojpur",
            "284",
            "32",
            "2"
        ],
        [
            "Bihar",
            "Buxar",
            "158",
            "27",
            "0"
        ],
        [
            "Bihar",
            "Darbhanga",
            "261",
            "64",
            "2"
        ],
        [
            "Bihar",
            "Gaya",
            "439",
            "68",
            "2"
        ],
        [
            "Bihar",
            "Gopalganj",
            "186",
            "32",
            "3"
        ],
        [
            "Bihar",
            "Jamui",
            "166",
            "28",
            "3"
        ],
        [
            "Bihar",
            "Jehanabad ",
            "81",
            "29",
            "2"
        ],
        [
            "Bihar",
            "Kaimur (Bhabua)",
            "107",
            "49",
            "2"
        ],
        [
            "Bihar",
            "Katihar",
            "257",
            "43",
            "3"
        ],
        [
            "Bihar",
            "Khagaria",
            "151",
            "24",
            "1"
        ],
        [
            "Bihar",
            "Kishanganj",
            "136",
            "15",
            "2"
        ],
        [
            "Bihar",
            "Lakhisarai",
            "102",
            "17",
            "1"
        ],
        [
            "Bihar",
            "Madhepura",
            "115",
            "30",
            "1"
        ],
        [
            "Bihar",
            "Madhubani",
            "430",
            "95",
            "2"
        ],
        [
            "Bihar",
            "Munger",
            "123",
            "19",
            "1"
        ],
        [
            "Bihar",
            "Muzaffarpur",
            "473",
            "61",
            "1"
        ],
        [
            "Bihar",
            "Nalanda",
            "302",
            "48",
            "3"
        ],
        [
            "Bihar",
            "Nawada",
            "129",
            "37",
            "2"
        ],
        [
            "Bihar",
            "Pashchim Champaran",
            "389",
            "41",
            "2"
        ],
        [
            "Bihar",
            "Patna",
            "418",
            "86",
            "4"
        ],
        [
            "Bihar",
            "Purba Champaran",
            "315",
            "66",
            "3"
        ],
        [
            "Bihar",
            "Purnia",
            "278",
            "45",
            "2"
        ],
        [
            "Bihar",
            "Rohtas",
            "186",
            "30",
            "1"
        ],
        [
            "Bihar",
            "Saharsa",
            "152",
            "40",
            "0"
        ],
        [
            "Bihar",
            "Samastipur",
            "354",
            "73",
            "1"
        ],
        [
            "Bihar",
            "Saran",
            "413",
            "60",
            "3"
        ],
        [
            "Bihar",
            "Sheikhpura",
            "74",
            "21",
            "1"
        ],
        [
            "Bihar",
            "Sheohar",
            "34",
            "10",
            "1"
        ],
        [
            "Bihar",
            "Sitamarhi",
            "213",
            "51",
            "1"
        ],
        [
            "Bihar",
            "Siwan",
            "370",
            "49",
            "2"
        ],
        [
            "Bihar",
            "Supaul",
            "178",
            "37",
            "1"
        ],
        [
            "Bihar",
            "Vaishali",
            "336",
            "47",
            "2"
        ],
        [
            "Bihar",
            "Total",
            "8858",
            "1641",
            "70"
        ],
        [
            "Chandigarh ",
            "Chandigarh",
            "13",
            "0",
            "1"
        ],
        [
            "Chhatisgarh",
            "Bastar",
            "372",
            "54",
            "11"
        ],
        [
            "Chhatisgarh",
            "Bilaspur",
            "357",
            "41",
            "10"
        ],
        [
            "Chhatisgarh",
            "Dantewada",
            "240",
            "34",
            "9"
        ],
        [
            "Chhatisgarh",
            "Dhamtari",
            "166",
            "12",
            "3"
        ],
        [
            "Chhatisgarh",
            "Durg",
            "441",
            "52",
            "10"
        ],
        [
            "Chhatisgarh",
            "Janjgir-Champa",
            "246",
            "24",
            "6"
        ],
        [
            "Chhatisgarh",
            "Jashpur",
            "239",
            "27",
            "7"
        ],
        [
            "Chhatisgarh",
            "Kanker",
            "205",
            "24",
            "7"
        ],
        [
            "Chhatisgarh",
            "Kawardha",
            "139",
            "12",
            "2"
        ],
        [
            "Chhatisgarh",
            "Korba",
            "211",
            "29",
            "3"
        ],
        [
            "Chhatisgarh",
            "Koriya",
            "136",
            "21",
            "5"
        ],
        [
            "Chhatisgarh",
            "Mahasamund",
            "213",
            "14",
            "4"
        ],
        [
            "Chhatisgarh",
            "Raigarh",
            "308",
            "40",
            "5"
        ],
        [
            "Chhatisgarh",
            "Raipur",
            "540",
            "47",
            "11"
        ],
        [
            "Chhatisgarh",
            "Rajnandgaon",
            "312",
            "25",
            "6"
        ],
        [
            "Chhatisgarh",
            "Surguja",
            "567",
            "65",
            "18"
        ],
        [
            "Chhatisgarh",
            "Total",
            "4692",
            "521",
            "117"
        ],
        [
            "Dadra & Nagar Haveli ",
            "Dadra & Nagar Haveli",
            "38",
            "6",
            "1"
        ],
        [
            "Daman & Diu ",
            "Daman",
            "15",
            "2",
            "1"
        ],
        [
            "Daman & Diu ",
            "Diu",
            "6",
            "1",
            "0"
        ],
        [
            "Daman & Diu ",
            "Total",
            "21",
            "3",
            "1"
        ],
        [
            "Delhi ",
            "East",
            "0",
            "0",
            "0"
        ],
        [
            "Delhi ",
            "North-East",
            "0",
            "0",
            "0"
        ],
        [
            "Delhi ",
            "North",
            "0",
            "0",
            "0"
        ],
        [
            "Delhi ",
            "North-West",
            "15",
            "3",
            "0"
        ],
        [
            "Delhi ",
            "West",
            "0",
            "0",
            "0"
        ],
        [
            "Delhi ",
            "South-West",
            "16",
            "3",
            "0"
        ],
        [
            "Delhi ",
            "South",
            "10",
            "2",
            "0"
        ],
        [
            "Delhi ",
            "Central",
            "0",
            "0",
            "0"
        ],
        [
            "Delhi ",
            "New Delhi",
            "0",
            "0",
            "0"
        ],
        [
            "Delhi ",
            "Total",
            "41",
            "8",
            "0"
        ],
        [
            "Goa",
            "North Goa ",
            "103",
            "11",
            "3"
        ],
        [
            "Goa",
            "South Goa",
            "69",
            "8",
            "2"
        ],
        [
            "Goa",
            "Total",
            "172",
            "19",
            "5"
        ],
        [
            "Gujarat",
            "Ahmadabad",
            "279",
            "43",
            "9"
        ],
        [
            "Gujarat",
            "Amreli",
            "247",
            "35",
            "13"
        ],
        [
            "Gujarat",
            "Anand",
            "274",
            "43",
            "10"
        ],
        [
            "Gujarat",
            "Banas Kantha",
            "422",
            "64",
            "13"
        ],
        [
            "Gujarat",
            "Bharuch",
            "200",
            "39",
            "8"
        ],
        [
            "Gujarat",
            "Bhavnagar",
            "360",
            "42",
            "14"
        ],
        [
            "Gujarat",
            "Dohad",
            "332",
            "61",
            "11"
        ],
        [
            "Gujarat",
            "Gandhinagar",
            "171",
            "24",
            "6"
        ],
        [
            "Gujarat",
            "Jamnagar",
            "265",
            "36",
            "11"
        ],
        [
            "Gujarat",
            "Junagadh",
            "390",
            "54",
            "15"
        ],
        [
            "Gujarat",
            "Kachchh",
            "251",
            "37",
            "12"
        ],
        [
            "Gujarat",
            "Kheda",
            "317",
            "50",
            "11"
        ],
        [
            "Gujarat",
            "Mahesana",
            "288",
            "48",
            "13"
        ],
        [
            "Gujarat",
            "Narmada",
            "116",
            "21",
            "4"
        ],
        [
            "Gujarat",
            "Navsari",
            "281",
            "36",
            "10"
        ],
        [
            "Gujarat",
            "Panch Mahals",
            "400",
            "64",
            "14"
        ],
        [
            "Gujarat",
            "Patan",
            "210",
            "29",
            "7"
        ],
        [
            "Gujarat",
            "Porbandar",
            "85",
            "10",
            "3"
        ],
        [
            "Gujarat",
            "Rajkot",
            "330",
            "43",
            "17"
        ],
        [
            "Gujarat",
            "Sabar Kantha",
            "413",
            "62",
            "18"
        ],
        [
            "Gujarat",
            "Surat",
            "601",
            "78",
            "17"
        ],
        [
            "Gujarat",
            "Surendranagar",
            "200",
            "31",
            "10"
        ],
        [
            "Gujarat",
            "The Dangs",
            "47",
            "7",
            "1"
        ],
        [
            "Gujarat",
            "Vadodara",
            "465",
            "76",
            "16"
        ],
        [
            "Gujarat",
            "Valsad",
            "330",
            "39",
            "10"
        ],
        [
            "Gujarat",
            "Total",
            "7274",
            "1072",
            "273"
        ],
        [
            "Haryana",
            "Ambala",
            "99",
            "15",
            "2"
        ],
        [
            "Haryana",
            "Bhiwani",
            "211",
            "37",
            "7"
        ],
        [
            "Haryana",
            "Faridabad",
            "106",
            "18",
            "2"
        ],
        [
            "Haryana",
            "Fatehabad",
            "102",
            "16",
            "3"
        ],
        [
            "Haryana",
            "Gurgaon",
            "71",
            "12",
            "2"
        ],
        [
            "Haryana",
            "Hisar",
            "199",
            "34",
            "7"
        ],
        [
            "Haryana",
            "Jhajjar",
            "123",
            "19",
            "3"
        ],
        [
            "Haryana",
            "Jind",
            "158",
            "27",
            "6"
        ],
        [
            "Haryana",
            "Kaithal",
            "144",
            "22",
            "4"
        ],
        [
            "Haryana",
            "Karnal",
            "141",
            "26",
            "5"
        ],
        [
            "Haryana",
            "Kurukshetra",
            "105",
            "17",
            "3"
        ],
        [
            "Haryana",
            "Mahendragarh\/Narnaul",
            "102",
            "21",
            "4"
        ],
        [
            "Haryana",
            "Mewat",
            "111",
            "17",
            "4"
        ],
        [
            "Haryana",
            "Panchkula",
            "48",
            "9",
            "2"
        ],
        [
            "Haryana",
            "Panipat",
            "89",
            "15",
            "2"
        ],
        [
            "Haryana",
            "Rewari",
            "105",
            "14",
            "5"
        ],
        [
            "Haryana",
            "Rohtak",
            "111",
            "21",
            "5"
        ],
        [
            "Haryana",
            "Sirsa",
            "137",
            "23",
            "4"
        ],
        [
            "Haryana",
            "Sonipat",
            "160",
            "27",
            "7"
        ],
        [
            "Haryana",
            "Yamunanagar",
            "111",
            "18",
            "4"
        ],
        [
            "Haryana",
            "Total",
            "2433",
            "408",
            "81"
        ],
        [
            "Himachal Pradesh",
            "Bilaspur",
            "117",
            "27",
            "5"
        ],
        [
            "Himachal Pradesh",
            "Chamba",
            "169",
            "40",
            "7"
        ],
        [
            "Himachal Pradesh",
            "Hamirpur",
            "152",
            "24",
            "5"
        ],
        [
            "Himachal Pradesh",
            "Kangra",
            "434",
            "78",
            "13"
        ],
        [
            "Himachal Pradesh",
            "Kinnaur",
            "33",
            "17",
            "3"
        ],
        [
            "Himachal Pradesh",
            "Kullu",
            "100",
            "17",
            "5"
        ],
        [
            "Himachal Pradesh",
            "Lahul & Spiti",
            "35",
            "14",
            "3"
        ],
        [
            "Himachal Pradesh",
            "Mandi",
            "311",
            "59",
            "9"
        ],
        [
            "Himachal Pradesh",
            "Shimla",
            "261",
            "77",
            "6"
        ],
        [
            "Himachal Pradesh",
            "Sirmaur",
            "148",
            "34",
            "3"
        ],
        [
            "Himachal Pradesh",
            "Solan",
            "178",
            "32",
            "3"
        ],
        [
            "Himachal Pradesh",
            "Una",
            "131",
            "20",
            "4"
        ],
        [
            "Himachal Pradesh",
            "Total",
            "2069",
            "439",
            "66"
        ],
        [
            "Jammu & Kashmir",
            "Anantanag",
            "191",
            "44",
            "8"
        ],
        [
            "Jammu & Kashmir",
            "Badgam",
            "121",
            "36",
            "9"
        ],
        [
            "Jammu & Kashmir",
            "Baramula",
            "151",
            "32",
            "7"
        ],
        [
            "Jammu & Kashmir",
            "Doda",
            "145",
            "28",
            "6"
        ],
        [
            "Jammu & Kashmir",
            "Jammu",
            "255",
            "36",
            "8"
        ],
        [
            "Jammu & Kashmir",
            "Kargil",
            "34",
            "2",
            "4"
        ],
        [
            "Jammu & Kashmir",
            "Kathua",
            "158",
            "28",
            "4"
        ],
        [
            "Jammu & Kashmir",
            "Kupwara",
            "154",
            "31",
            "7"
        ],
        [
            "Jammu & Kashmir",
            "Leh (Ladakh)",
            "58",
            "15",
            "3"
        ],
        [
            "Jammu & Kashmir",
            "Pulwama",
            "129",
            "24",
            "6"
        ],
        [
            "Jammu & Kashmir",
            "Poonch",
            "97",
            "17",
            "3"
        ],
        [
            "Jammu & Kashmir",
            "Rajauri",
            "139",
            "21",
            "6"
        ],
        [
            "Jammu & Kashmir",
            "Srinagar",
            "83",
            "24",
            "3"
        ],
        [
            "Jammu & Kashmir",
            "Udhampur",
            "173",
            "36",
            "6"
        ],
        [
            "Jammu & Kashmir",
            "Total",
            "1888",
            "374",
            "80"
        ],
        [
            "Jharkhand",
            "Bokaro",
            "116",
            "16",
            "8"
        ],
        [
            "Jharkhand",
            "Chatra",
            "93",
            "8",
            "6"
        ],
        [
            "Jharkhand",
            "Deoghar",
            "181",
            "5",
            "8"
        ],
        [
            "Jharkhand",
            "Dhanbad",
            "137",
            "28",
            "8"
        ],
        [
            "Jharkhand",
            "Dumka",
            "258",
            "36",
            "10"
        ],
        [
            "Jharkhand",
            "E. Singhbhum",
            "244",
            "16",
            "9"
        ],
        [
            "Jharkhand",
            "Garhwa",
            "111",
            "10",
            "8"
        ],
        [
            "Jharkhand",
            "Giridih",
            "180",
            "15",
            "12"
        ],
        [
            "Jharkhand",
            "Godda",
            "195",
            "21",
            "7"
        ],
        [
            "Jharkhand",
            "Gumla",
            "242",
            "13",
            "11"
        ],
        [
            "Jharkhand",
            "Hazaribagh",
            "203",
            "19",
            "14"
        ],
        [
            "Jharkhand",
            "Jamtara",
            "132",
            "15",
            "4"
        ],
        [
            "Jharkhand",
            "Koderma",
            "65",
            "5",
            "4"
        ],
        [
            "Jharkhand",
            "Latehar",
            "101",
            "7",
            "7"
        ],
        [
            "Jharkhand",
            "Lohardaga",
            "73",
            "10",
            "5"
        ],
        [
            "Jharkhand",
            "Pakur",
            "121",
            "9",
            "6"
        ],
        [
            "Jharkhand",
            "Palamu",
            "172",
            "21",
            "10"
        ],
        [
            "Jharkhand",
            "Ranchi",
            "502",
            "32",
            "20"
        ],
        [
            "Jharkhand",
            "Sahibganj",
            "141",
            "10",
            "7"
        ],
        [
            "Jharkhand",
            "Saraikela",
            "194",
            "12",
            "8"
        ],
        [
            "Jharkhand",
            "Simdega",
            "155",
            "7",
            "7"
        ],
        [
            "Jharkhand",
            "W. Singhbhum",
            "342",
            "15",
            "15"
        ],
        [
            "Jharkhand",
            "Total",
            "3958",
            "330",
            "194"
        ],
        [
            "Karnataka",
            "Bagalkot",
            "224",
            "46",
            "10"
        ],
        [
            "Karnataka",
            "Bangalore",
            "185",
            "31",
            "3"
        ],
        [
            "Karnataka",
            "Bangalore Rural",
            "432",
            "73",
            "11"
        ],
        [
            "Karnataka",
            "Belgaum",
            "539",
            "135",
            "16"
        ],
        [
            "Karnataka",
            "Bellary",
            "272",
            "53",
            "9"
        ],
        [
            "Karnataka",
            "Bidar",
            "234",
            "41",
            "6"
        ],
        [
            "Karnataka",
            "Bijapur",
            "285",
            "63",
            "9"
        ],
        [
            "Karnataka",
            "Chamarajanagar",
            "246",
            "51",
            "5"
        ],
        [
            "Karnataka",
            "Chikmagalur",
            "334",
            "51",
            "8"
        ],
        [
            "Karnataka",
            "Chitradurga",
            "273",
            "57",
            "12"
        ],
        [
            "Karnataka",
            "Dakshina Kannada",
            "431",
            "65",
            "8"
        ],
        [
            "Karnataka",
            "Davanagere",
            "291",
            "70",
            "7"
        ],
        [
            "Karnataka",
            "Dharwad",
            "179",
            "28",
            "3"
        ],
        [
            "Karnataka",
            "Gadag",
            "174",
            "29",
            "6"
        ],
        [
            "Karnataka",
            "Gulbarga",
            "378",
            "108",
            "19"
        ],
        [
            "Karnataka",
            "Hassan",
            "420",
            "83",
            "15"
        ],
        [
            "Karnataka",
            "Haveri",
            "290",
            "50",
            "11"
        ],
        [
            "Karnataka",
            "Kodagu",
            "188",
            "29",
            "8"
        ],
        [
            "Karnataka",
            "Kolar",
            "385",
            "82",
            "13"
        ],
        [
            "Karnataka",
            "Koppal",
            "183",
            "43",
            "9"
        ],
        [
            "Karnataka",
            "Mandya",
            "375",
            "71",
            "9"
        ],
        [
            "Karnataka",
            "Mysore",
            "432",
            "96",
            "15"
        ],
        [
            "Karnataka",
            "Raichur",
            "196",
            "47",
            "5"
        ],
        [
            "Karnataka",
            "Shimoga",
            "307",
            "56",
            "9"
        ],
        [
            "Karnataka",
            "Tumkur",
            "477",
            "98",
            "10"
        ],
        [
            "Karnataka",
            "Udupi",
            "293",
            "62",
            "6"
        ],
        [
            "Karnataka",
            "Uttara Kannada",
            "120",
            "61",
            "12"
        ],
        [
            "Karnataka",
            "Total",
            "8143",
            "1679",
            "254"
        ],
        [
            "Kerala",
            "Alappuzha",
            "368",
            "65",
            "7"
        ],
        [
            "Kerala",
            "Ernakulam",
            "351",
            "74",
            "9"
        ],
        [
            "Kerala",
            "Idukki",
            "231",
            "52",
            "6"
        ],
        [
            "Kerala",
            "Kannur",
            "352",
            "79",
            "7"
        ],
        [
            "Kerala",
            "Kasaragod",
            "205",
            "46",
            "5"
        ],
        [
            "Kerala",
            "Kollam",
            "449",
            "60",
            "8"
        ],
        [
            "Kerala",
            "Kottayam",
            "359",
            "60",
            "7"
        ],
        [
            "Kerala",
            "Kozhikode",
            "389",
            "69",
            "10"
        ],
        [
            "Kerala",
            "Malappuram",
            "508",
            "94",
            "10"
        ],
        [
            "Kerala",
            "Palakkad",
            "471",
            "81",
            "12"
        ],
        [
            "Kerala",
            "Pathanamthitta",
            "260",
            "50",
            "3"
        ],
        [
            "Kerala",
            "Thiruvananthapuram",
            "455",
            "71",
            "9"
        ],
        [
            "Kerala",
            "Thrissur",
            "492",
            "84",
            "9"
        ],
        [
            "Kerala",
            "Wayanad",
            "204",
            "24",
            "5"
        ],
        [
            "Kerala",
            "Total",
            "5094",
            "909",
            "107"
        ],
        [
            "Lakshadweep ",
            "Lakshadweep",
            "14",
            "4",
            "3"
        ],
        [
            "Madhya Pradesh",
            "Balaghat",
            "240",
            "31",
            "5"
        ],
        [
            "Madhya Pradesh",
            "Barwani",
            "286",
            "35",
            "6"
        ],
        [
            "Madhya Pradesh",
            "Betul",
            "271",
            "34",
            "6"
        ],
        [
            "Madhya Pradesh",
            "Bhind",
            "183",
            "19",
            "7"
        ],
        [
            "Madhya Pradesh",
            "Bhopal",
            "63",
            "10",
            "2"
        ],
        [
            "Madhya Pradesh",
            "Chhatarpur",
            "189",
            "41",
            "4"
        ],
        [
            "Madhya Pradesh",
            "Chhindwara",
            "317",
            "67",
            "11"
        ],
        [
            "Madhya Pradesh",
            "Damoh",
            "162",
            "15",
            "1"
        ],
        [
            "Madhya Pradesh",
            "Datia",
            "87",
            "11",
            "1"
        ],
        [
            "Madhya Pradesh",
            "Dewas",
            "192",
            "25",
            "2"
        ],
        [
            "Madhya Pradesh",
            "Dhar",
            "400",
            "50",
            "10"
        ],
        [
            "Madhya Pradesh",
            "Dindori",
            "183",
            "24",
            "8"
        ],
        [
            "Madhya Pradesh",
            "East Nimar",
            "271",
            "46",
            "7"
        ],
        [
            "Madhya Pradesh",
            "Guna",
            "216",
            "24",
            "6"
        ],
        [
            "Madhya Pradesh",
            "Gwalior",
            "101",
            "15",
            "3"
        ],
        [
            "Madhya Pradesh",
            "Harda",
            "61",
            "7",
            "2"
        ],
        [
            "Madhya Pradesh",
            "Hoshangabad",
            "143",
            "16",
            "5"
        ],
        [
            "Madhya Pradesh",
            "Indore",
            "111",
            "26",
            "3"
        ],
        [
            "Madhya Pradesh",
            "Jabalpur",
            "193",
            "16",
            "5"
        ],
        [
            "Madhya Pradesh",
            "Jhabua",
            "346",
            "32",
            "10"
        ],
        [
            "Madhya Pradesh",
            "Katni",
            "162",
            "19",
            "5"
        ],
        [
            "Madhya Pradesh",
            "Mandla",
            "215",
            "28",
            "7"
        ],
        [
            "Madhya Pradesh",
            "Mandsaur",
            "153",
            "46",
            "0"
        ],
        [
            "Madhya Pradesh",
            "Morena",
            "196",
            "19",
            "4"
        ],
        [
            "Madhya Pradesh",
            "Narsimhapur",
            "144",
            "19",
            "5"
        ],
        [
            "Madhya Pradesh",
            "Neemuch",
            "105",
            "18",
            "1"
        ],
        [
            "Madhya Pradesh",
            "Panna",
            "140",
            "15",
            "4"
        ],
        [
            "Madhya Pradesh",
            "Raisen",
            "175",
            "23",
            "5"
        ],
        [
            "Madhya Pradesh",
            "Rajgarh",
            "166",
            "31",
            "4"
        ],
        [
            "Madhya Pradesh",
            "Ratlam",
            "166",
            "26",
            "3"
        ],
        [
            "Madhya Pradesh",
            "Rewa",
            "268",
            "30",
            "9"
        ],
        [
            "Madhya Pradesh",
            "Sagar",
            "245",
            "29",
            "9"
        ],
        [
            "Madhya Pradesh",
            "Satna",
            "258",
            "45",
            "6"
        ],
        [
            "Madhya Pradesh",
            "Sehore",
            "152",
            "17",
            "5"
        ],
        [
            "Madhya Pradesh",
            "Seoni",
            "284",
            "29",
            "8"
        ],
        [
            "Madhya Pradesh",
            "Shahdol",
            "413",
            "47",
            "10"
        ],
        [
            "Madhya Pradesh",
            "Shajapur",
            "173",
            "21",
            "5"
        ],
        [
            "Madhya Pradesh",
            "Sheopur",
            "89",
            "8",
            "3"
        ],
        [
            "Madhya Pradesh",
            "Shivpuri",
            "199",
            "13",
            "6"
        ],
        [
            "Madhya Pradesh",
            "Sidhi",
            "302",
            "42",
            "8"
        ],
        [
            "Madhya Pradesh",
            "Tikamgarh",
            "156",
            "18",
            "5"
        ],
        [
            "Madhya Pradesh",
            "Ujjain",
            "170",
            "21",
            "2"
        ],
        [
            "Madhya Pradesh",
            "Umaria",
            "87",
            "11",
            "1"
        ],
        [
            "Madhya Pradesh",
            "Vidisha",
            "144",
            "20",
            "4"
        ],
        [
            "Madhya Pradesh",
            "West Nimar\/Khargaon",
            "297",
            "53",
            "6"
        ],
        [
            "Madhya Pradesh",
            "Total",
            "8874",
            "1192",
            "229"
        ],
        [
            "Maharashtra",
            "Ahmadnagar",
            "551",
            "97",
            "21"
        ],
        [
            "Maharashtra",
            "Akola",
            "173",
            "30",
            "6"
        ],
        [
            "Maharashtra",
            "Amravati",
            "330",
            "56",
            "13"
        ],
        [
            "Maharashtra",
            "Aurangabad",
            "277",
            "50",
            "8"
        ],
        [
            "Maharashtra",
            "Bhandara",
            "190",
            "33",
            "8"
        ],
        [
            "Maharashtra",
            "Beed",
            "278",
            "50",
            "13"
        ],
        [
            "Maharashtra",
            "Buldana",
            "279",
            "52",
            "14"
        ],
        [
            "Maharashtra",
            "Chandrapur",
            "336",
            "58",
            "13"
        ],
        [
            "Maharashtra",
            "Dhule",
            "228",
            "41",
            "7"
        ],
        [
            "Maharashtra",
            "Gadchiroli",
            "374",
            "45",
            "12"
        ],
        [
            "Maharashtra",
            "Gondiya",
            "237",
            "39",
            "10"
        ],
        [
            "Maharashtra",
            "Hingoli",
            "135",
            "24",
            "5"
        ],
        [
            "Maharashtra",
            "Jalgaon",
            "439",
            "78",
            "20"
        ],
        [
            "Maharashtra",
            "Jalna",
            "211",
            "38",
            "9"
        ],
        [
            "Maharashtra",
            "Kolhapur",
            "409",
            "72",
            "17"
        ],
        [
            "Maharashtra",
            "Latur",
            "248",
            "46",
            "11"
        ],
        [
            "Maharashtra",
            "Nagpur",
            "301",
            "49",
            "11"
        ],
        [
            "Maharashtra",
            "Nanded",
            "374",
            "64",
            "14"
        ],
        [
            "Maharashtra",
            "Nandurbar",
            "257",
            "49",
            "12"
        ],
        [
            "Maharashtra",
            "Nashik",
            "571",
            "103",
            "26"
        ],
        [
            "Maharashtra",
            "Osmanabad",
            "204",
            "42",
            "8"
        ],
        [
            "Maharashtra",
            "Parbhani",
            "216",
            "31",
            "8"
        ],
        [
            "Maharashtra",
            "Pune",
            "535",
            "95",
            "23"
        ],
        [
            "Maharashtra",
            "Raigarh",
            "286",
            "52",
            "13"
        ],
        [
            "Maharashtra",
            "Ratnagiri",
            "374",
            "67",
            "10"
        ],
        [
            "Maharashtra",
            "Sangli",
            "317",
            "59",
            "11"
        ],
        [
            "Maharashtra",
            "Satara",
            "397",
            "71",
            "14"
        ],
        [
            "Maharashtra",
            "Sindhudurg",
            "246",
            "38",
            "10"
        ],
        [
            "Maharashtra",
            "Solapur",
            "428",
            "77",
            "13"
        ],
        [
            "Maharashtra",
            "Thane",
            "487",
            "79",
            "14"
        ],
        [
            "Maharashtra",
            "Wardha",
            "180",
            "27",
            "8"
        ],
        [
            "Maharashtra",
            "Washim",
            "153",
            "25",
            "8"
        ],
        [
            "Maharashtra",
            "Yavatmal",
            "432",
            "63",
            "17"
        ],
        [
            "Maharashtra",
            "Total",
            "10453",
            "1800",
            "407"
        ],
        [
            "Manipur",
            "Bishnupur",
            "36",
            "5",
            "2"
        ],
        [
            "Manipur",
            "Chandel",
            "26",
            "3",
            "1"
        ],
        [
            "Manipur",
            "Churachandpur",
            "61",
            "9",
            "1"
        ],
        [
            "Manipur",
            "Imphal East",
            "53",
            "11",
            "2"
        ],
        [
            "Manipur",
            "Imphal West",
            "51",
            "8",
            "2"
        ],
        [
            "Manipur",
            "Senapati",
            "66",
            "12",
            "2"
        ],
        [
            "Manipur",
            "Tamenglong",
            "29",
            "6",
            "1"
        ],
        [
            "Manipur",
            "Thoubal",
            "58",
            "12",
            "4"
        ],
        [
            "Manipur",
            "Ukhrul",
            "40",
            "6",
            "1"
        ],
        [
            "Manipur",
            "Total",
            "420",
            "72",
            "16"
        ],
        [
            "Meghalaya",
            "East Garo Hills",
            "69",
            "17",
            "2"
        ],
        [
            "Meghalaya",
            "East Khasi Hills",
            "68",
            "20",
            "5"
        ],
        [
            "Meghalaya",
            "Jaintia Hills",
            "70",
            "16",
            "5"
        ],
        [
            "Meghalaya",
            "Ri Bhoi",
            "26",
            "8",
            "3"
        ],
        [
            "Meghalaya",
            "South Garo Hills",
            "22",
            "7",
            "1"
        ],
        [
            "Meghalaya",
            "West Garo Hills",
            "81",
            "18",
            "6"
        ],
        [
            "Meghalaya",
            "West Khasi Hills",
            "65",
            "15",
            "3"
        ],
        [
            "Meghalaya",
            "Total",
            "401",
            "101",
            "25"
        ],
        [
            "Mizoram",
            "Aizawl(West)",
            "50",
            "4",
            "0"
        ],
        [
            "Mizoram",
            "Aizwal(East)",
            "37",
            "5",
            "2"
        ],
        [
            "Mizoram",
            "Champhai",
            "58",
            "12",
            "2"
        ],
        [
            "Mizoram",
            "Kolasib",
            "29",
            "5",
            "1"
        ],
        [
            "Mizoram",
            "Lawngtlai",
            "26",
            "2",
            "1"
        ],
        [
            "Mizoram",
            "Lunglei",
            "70",
            "9",
            "1"
        ],
        [
            "Mizoram",
            "Mamit",
            "34",
            "8",
            "1"
        ],
        [
            "Mizoram",
            "Saiha",
            "34",
            "7",
            "0"
        ],
        [
            "Mizoram",
            "Serchhip",
            "28",
            "5",
            "1"
        ],
        [
            "Mizoram",
            "Total",
            "366",
            "57",
            "9"
        ],
        [
            "Nagaland",
            "Dimapur",
            "47",
            "5",
            "2"
        ],
        [
            "Nagaland",
            "Kohima",
            "39",
            "12",
            "3"
        ],
        [
            "Nagaland",
            "Kiphere",
            "19",
            "1",
            "1"
        ],
        [
            "Nagaland",
            "Longleng",
            "8",
            "2",
            "0"
        ],
        [
            "Nagaland",
            "Mokokchung",
            "51",
            "11",
            "3"
        ],
        [
            "Nagaland",
            "Mon",
            "50",
            "8",
            "2"
        ],
        [
            "Nagaland",
            "Phek",
            "44",
            "17",
            "3"
        ],
        [
            "Nagaland",
            "Peren",
            "16",
            "4",
            "1"
        ],
        [
            "Nagaland",
            "Tuensang",
            "39",
            "8",
            "2"
        ],
        [
            "Nagaland",
            "Wokha",
            "37",
            "7",
            "2"
        ],
        [
            "Nagaland",
            "Zunheboto",
            "47",
            "9",
            "2"
        ],
        [
            "Nagaland",
            "Total",
            "397",
            "84",
            "21"
        ],
        [
            "Orissa",
            "Anugul",
            "146",
            "32",
            "4"
        ],
        [
            "Orissa",
            "Balangir",
            "203",
            "44",
            "8"
        ],
        [
            "Orissa",
            "Baleshwar",
            "250",
            "72",
            "9"
        ],
        [
            "Orissa",
            "Bargarh",
            "187",
            "49",
            "8"
        ],
        [
            "Orissa",
            "Baudh",
            "59",
            "12",
            "1"
        ],
        [
            "Orissa",
            "Bhadrak",
            "159",
            "50",
            "6"
        ],
        [
            "Orissa",
            "Cuttack",
            "299",
            "57",
            "9"
        ],
        [
            "Orissa",
            "Debagarh",
            "35",
            "8",
            "2"
        ],
        [
            "Orissa",
            "Dhenkanal",
            "150",
            "36",
            "6"
        ],
        [
            "Orissa",
            "Gajapati",
            "116",
            "20",
            "5"
        ],
        [
            "Orissa",
            "Ganjam",
            "424",
            "89",
            "19"
        ],
        [
            "Orissa",
            "Jagatsinghapur",
            "182",
            "38",
            "6"
        ],
        [
            "Orissa",
            "Jajapur",
            "235",
            "56",
            "9"
        ],
        [
            "Orissa",
            "Jharsuguda",
            "58",
            "17",
            "3"
        ],
        [
            "Orissa",
            "Kalahandi",
            "213",
            "43",
            "10"
        ],
        [
            "Orissa",
            "Kandhamal",
            "151",
            "39",
            "8"
        ],
        [
            "Orissa",
            "Kendrapara",
            "209",
            "44",
            "9"
        ],
        [
            "Orissa",
            "Kendujhar",
            "316",
            "61",
            "11"
        ],
        [
            "Orissa",
            "Khordha",
            "186",
            "63",
            "7"
        ],
        [
            "Orissa",
            "Koraput",
            "253",
            "51",
            "9"
        ],
        [
            "Orissa",
            "Malkangiri",
            "134",
            "28",
            "5"
        ],
        [
            "Orissa",
            "Mayurbhanj",
            "521",
            "85",
            "17"
        ],
        [
            "Orissa",
            "Nabarangapur",
            "222",
            "40",
            "7"
        ],
        [
            "Orissa",
            "Nayagarh",
            "150",
            "34",
            "6"
        ],
        [
            "Orissa",
            "Nuapada",
            "85",
            "17",
            "4"
        ],
        [
            "Orissa",
            "Puri",
            "221",
            "46",
            "9"
        ],
        [
            "Orissa",
            "Rayagada",
            "200",
            "40",
            "5"
        ],
        [
            "Orissa",
            "Sambalpur",
            "142",
            "31",
            "9"
        ],
        [
            "Orissa",
            "Sonapur",
            "76",
            "18",
            "5"
        ],
        [
            "Orissa",
            "Sundargarh",
            "345",
            "59",
            "15"
        ],
        [
            "Orissa",
            "Total",
            "5927",
            "1279",
            "231"
        ],
        [
            "Pondicherry ",
            "Karaikal",
            "17",
            "11",
            "1"
        ],
        [
            "Pondicherry ",
            "Mahe",
            "4",
            "1",
            "1"
        ],
        [
            "Pondicherry ",
            "Pondicherry",
            "52",
            "27",
            "2"
        ],
        [
            "Pondicherry ",
            "Yanam",
            "4",
            "0",
            "0"
        ],
        [
            "Pondicherry ",
            "Total",
            "77",
            "39",
            "4"
        ],
        [
            "Punjab",
            "Amritsar",
            "332",
            "57",
            "13"
        ],
        [
            "Punjab",
            "Bathinda",
            "140",
            "24",
            "7"
        ],
        [
            "Punjab",
            "Faridkot",
            "61",
            "9",
            "2"
        ],
        [
            "Punjab",
            "Fatehgarh Sahib",
            "67",
            "14",
            "3"
        ],
        [
            "Punjab",
            "Firozpur",
            "211",
            "38",
            "10"
        ],
        [
            "Punjab",
            "Gurdaspur",
            "274",
            "47",
            "14"
        ],
        [
            "Punjab",
            "Hoshiarpur",
            "234",
            "37",
            "9"
        ],
        [
            "Punjab",
            "Jalandhar",
            "195",
            "30",
            "9"
        ],
        [
            "Punjab",
            "Kapurthala",
            "88",
            "14",
            "5"
        ],
        [
            "Punjab",
            "Ludhiana",
            "227",
            "37",
            "10"
        ],
        [
            "Punjab",
            "Mansa",
            "103",
            "16",
            "5"
        ],
        [
            "Punjab",
            "Moga",
            "131",
            "23",
            "5"
        ],
        [
            "Punjab",
            "Muktsar",
            "102",
            "17",
            "5"
        ],
        [
            "Punjab",
            "Nawanshahr",
            "95",
            "16",
            "3"
        ],
        [
            "Punjab",
            "Patiala",
            "207",
            "37",
            "10"
        ],
        [
            "Punjab",
            "Rupnagar",
            "128",
            "23",
            "6"
        ],
        [
            "Punjab",
            "Sangrur",
            "263",
            "45",
            "10"
        ],
        [
            "Punjab",
            "Total",
            "2858",
            "484",
            "126"
        ],
        [
            "Rajasthan",
            "Ajmer",
            "279",
            "48",
            "10"
        ],
        [
            "Rajasthan",
            "Alwar",
            "459",
            "83",
            "17"
        ],
        [
            "Rajasthan",
            "Banswara",
            "334",
            "57",
            "10"
        ],
        [
            "Rajasthan",
            "Baran",
            "197",
            "34",
            "8"
        ],
        [
            "Rajasthan",
            "Barmer",
            "421",
            "66",
            "9"
        ],
        [
            "Rajasthan",
            "Bharatpur",
            "362",
            "57",
            "8"
        ],
        [
            "Rajasthan",
            "Bhilwara",
            "391",
            "72",
            "14"
        ],
        [
            "Rajasthan",
            "Bikaner",
            "258",
            "45",
            "7"
        ],
        [
            "Rajasthan",
            "Bundi",
            "174",
            "28",
            "5"
        ],
        [
            "Rajasthan",
            "Chittaurgarh",
            "391",
            "64",
            "12"
        ],
        [
            "Rajasthan",
            "Churu",
            "307",
            "59",
            "8"
        ],
        [
            "Rajasthan",
            "Dausa",
            "232",
            "32",
            "6"
        ],
        [
            "Rajasthan",
            "Dhaulpur",
            "159",
            "25",
            "3"
        ],
        [
            "Rajasthan",
            "Dungarpur",
            "306",
            "43",
            "7"
        ],
        [
            "Rajasthan",
            "Ganganagar",
            "348",
            "44",
            "8"
        ],
        [
            "Rajasthan",
            "Hanumangarh",
            "245",
            "42",
            "7"
        ],
        [
            "Rajasthan",
            "Jaipur",
            "506",
            "93",
            "15"
        ],
        [
            "Rajasthan",
            "Jaisalmer",
            "125",
            "16",
            "3"
        ],
        [
            "Rajasthan",
            "Jalor",
            "298",
            "56",
            "8"
        ],
        [
            "Rajasthan",
            "Jhalawar",
            "228",
            "35",
            "11"
        ],
        [
            "Rajasthan",
            "Jhunjhunun",
            "338",
            "76",
            "12"
        ],
        [
            "Rajasthan",
            "Jodhpur",
            "467",
            "75",
            "13"
        ],
        [
            "Rajasthan",
            "Karauli",
            "225",
            "27",
            "5"
        ],
        [
            "Rajasthan",
            "Kota",
            "159",
            "30",
            "9"
        ],
        [
            "Rajasthan",
            "Nagaur",
            "533",
            "94",
            "14"
        ],
        [
            "Rajasthan",
            "Pali",
            "401",
            "71",
            "12"
        ],
        [
            "Rajasthan",
            "Rajsamand",
            "205",
            "40",
            "7"
        ],
        [
            "Rajasthan",
            "Sawai Madhopur",
            "197",
            "26",
            "4"
        ],
        [
            "Rajasthan",
            "Sikar",
            "409",
            "74",
            "15"
        ],
        [
            "Rajasthan",
            "Sirohi",
            "187",
            "26",
            "6"
        ],
        [
            "Rajasthan",
            "Tonk",
            "246",
            "47",
            "7"
        ],
        [
            "Rajasthan",
            "Udaipur",
            "539",
            "90",
            "17"
        ],
        [
            "Rajasthan",
            "Total",
            "9926",
            "1675",
            "297"
        ],
        [
            "Sikkim",
            "East",
            "48",
            "8",
            "1"
        ],
        [
            "Sikkim",
            "North ",
            "19",
            "3",
            "1"
        ],
        [
            "Sikkim",
            "South",
            "39",
            "6",
            "1"
        ],
        [
            "Sikkim",
            "West",
            "41",
            "7",
            "1"
        ],
        [
            "Sikkim",
            "Total",
            "147",
            "24",
            "4"
        ],
        [
            "Tamil Nadu",
            "Ariyalur",
            "NA",
            "NA",
            "NA"
        ],
        [
            "Tamil Nadu",
            "Chennai",
            "0",
            "0",
            "NA"
        ],
        [
            "Tamil Nadu",
            "Coimbatore",
            "469",
            "66",
            "NA"
        ],
        [
            "Tamil Nadu",
            "Cuddalore",
            "319",
            "42",
            "NA"
        ],
        [
            "Tamil Nadu",
            "Dharmapuri",
            "447",
            "44",
            "NA"
        ],
        [
            "Tamil Nadu",
            "Dindigul",
            "305",
            "69",
            "NA"
        ],
        [
            "Tamil Nadu",
            "Erode",
            "412",
            "62",
            "NA"
        ],
        [
            "Tamil Nadu",
            "Kancheepuram",
            "352",
            "46",
            "NA"
        ],
        [
            "Tamil Nadu",
            "Kanniyakumari",
            "267",
            "25",
            "NA"
        ],
        [
            "Tamil Nadu",
            "Karur",
            "164",
            "26",
            "NA"
        ],
        [
            "Tamil Nadu",
            "Madurai",
            "302",
            "40",
            "NA"
        ],
        [
            "Tamil Nadu",
            "Nagapattinam",
            "184",
            "39",
            "NA"
        ],
        [
            "Tamil Nadu",
            "Namakkal",
            "240",
            "44",
            "NA"
        ],
        [
            "Tamil Nadu",
            "Perambalur",
            "203",
            "47",
            "NA"
        ],
        [
            "Tamil Nadu",
            "Pudukkottai",
            "239",
            "46",
            "NA"
        ],
        [
            "Tamil Nadu",
            "Ramanathapuram",
            "249",
            "41",
            "NA"
        ],
        [
            "Tamil Nadu",
            "Salem",
            "421",
            "67",
            "NA"
        ],
        [
            "Tamil Nadu",
            "Sivaganga",
            "267",
            "41",
            "NA"
        ],
        [
            "Tamil Nadu",
            "Thanjavur",
            "319",
            "55",
            "NA"
        ],
        [
            "Tamil Nadu",
            "The Nilgiris",
            "194",
            "26",
            "NA"
        ],
        [
            "Tamil Nadu",
            "Theni",
            "163",
            "23",
            "NA"
        ],
        [
            "Tamil Nadu",
            "Thiruvallur",
            "300",
            "39",
            "NA"
        ],
        [
            "Tamil Nadu",
            "Thiruvarur",
            "248",
            "38",
            "NA"
        ],
        [
            "Tamil Nadu",
            "Tiruchirappalli",
            "318",
            "44",
            "NA"
        ],
        [
            "Tamil Nadu",
            "Tirunelveli",
            "383",
            "59",
            "NA"
        ],
        [
            "Tamil Nadu",
            "Tiruvanamalai",
            "398",
            "78",
            "NA"
        ],
        [
            "Tamil Nadu",
            "Toothukudi",
            "249",
            "47",
            "NA"
        ],
        [
            "Tamil Nadu",
            "Vellore",
            "452",
            "64",
            "NA"
        ],
        [
            "Tamil Nadu",
            "Viluppuram",
            "557",
            "77",
            "NA"
        ],
        [
            "Tamil Nadu",
            "Virudhunagar",
            "261",
            "36",
            "NA"
        ],
        [
            "Tamil Nadu",
            "Total",
            "8682",
            "1331",
            "NA"
        ],
        [
            "Tripura",
            "Dhalai",
            "56",
            "11",
            "0"
        ],
        [
            "Tripura",
            "North Tripura ",
            "97",
            "19",
            "1"
        ],
        [
            "Tripura",
            "South Tripura ",
            "143",
            "22",
            "3"
        ],
        [
            "Tripura",
            "West Tripura ",
            "243",
            "21",
            "6"
        ],
        [
            "Tripura",
            "Total",
            "539",
            "73",
            "10"
        ],
        [
            "Uttar Pradesh",
            "Agra",
            "383",
            "68",
            "5"
        ],
        [
            "Uttar Pradesh",
            "Aligarh",
            "351",
            "38",
            "5"
        ],
        [
            "Uttar Pradesh",
            "Allahabad",
            "539",
            "88",
            "13"
        ],
        [
            "Uttar Pradesh",
            "Ambedkar Nagar",
            "232",
            "33",
            "4"
        ],
        [
            "Uttar Pradesh",
            "Auraiya",
            "164",
            "28",
            "3"
        ],
        [
            "Uttar Pradesh",
            "Azamgarh",
            "490",
            "101",
            "12"
        ],
        [
            "Uttar Pradesh",
            "Baghpat",
            "135",
            "27",
            "3"
        ],
        [
            "Uttar Pradesh",
            "Bahraich",
            "276",
            "51",
            "3"
        ],
        [
            "Uttar Pradesh",
            "Ballia",
            "366",
            "82",
            "9"
        ],
        [
            "Uttar Pradesh",
            "Balrampur",
            "214",
            "36",
            "4"
        ],
        [
            "Uttar Pradesh",
            "Banda",
            "285",
            "51",
            "4"
        ],
        [
            "Uttar Pradesh",
            "Barabanki",
            "353",
            "55",
            "7"
        ],
        [
            "Uttar Pradesh",
            "Bareilly",
            "413",
            "65",
            "6"
        ],
        [
            "Uttar Pradesh",
            "Basti",
            "267",
            "61",
            "4"
        ],
        [
            "Uttar Pradesh",
            "Bijnor",
            "353",
            "58",
            "7"
        ],
        [
            "Uttar Pradesh",
            "Badaun",
            "370",
            "70",
            "8"
        ],
        [
            "Uttar Pradesh",
            "Bulandshahar",
            "390",
            "78",
            "7"
        ],
        [
            "Uttar Pradesh",
            "Chandauli",
            "244",
            "40",
            "3"
        ],
        [
            "Uttar Pradesh",
            "Chitrakoot",
            "140",
            "29",
            "2"
        ],
        [
            "Uttar Pradesh",
            "Deoria",
            "364",
            "74",
            "8"
        ],
        [
            "Uttar Pradesh",
            "Etah",
            "345",
            "77",
            "7"
        ],
        [
            "Uttar Pradesh",
            "Etawah",
            "169",
            "49",
            "4"
        ],
        [
            "Uttar Pradesh",
            "Faizabad",
            "255",
            "43",
            "2"
        ],
        [
            "Uttar Pradesh",
            "Farrukhabad",
            "192",
            "29",
            "2"
        ],
        [
            "Uttar Pradesh",
            "Fatehpur",
            "309",
            "57",
            "5"
        ],
        [
            "Uttar Pradesh",
            "Firozabad",
            "240",
            "39",
            "2"
        ],
        [
            "Uttar Pradesh",
            "Gautam B. Nagar",
            "107",
            "16",
            "3"
        ],
        [
            "Uttar Pradesh",
            "Ghaziabad",
            "292",
            "46",
            "5"
        ],
        [
            "Uttar Pradesh",
            "Ghazipur",
            "393",
            "72",
            "8"
        ],
        [
            "Uttar Pradesh",
            "Gonda",
            "338",
            "59",
            "5"
        ],
        [
            "Uttar Pradesh",
            "Gorakhpur",
            "448",
            "87",
            "8"
        ],
        [
            "Uttar Pradesh",
            "Hamirpur",
            "215",
            "33",
            "1"
        ],
        [
            "Uttar Pradesh",
            "Hardoi",
            "432",
            "76",
            "6"
        ],
        [
            "Uttar Pradesh",
            "Hathras \/ Mahamaya Nagar",
            "147",
            "52",
            "4"
        ],
        [
            "Uttar Pradesh",
            "Jalaun",
            "286",
            "48",
            "4"
        ],
        [
            "Uttar Pradesh",
            "Jaunpur",
            "499",
            "93",
            "9"
        ],
        [
            "Uttar Pradesh",
            "Jhansi",
            "326",
            "44",
            "4"
        ],
        [
            "Uttar Pradesh",
            "Jyotibha Phule Nagar",
            "172",
            "32",
            "4"
        ],
        [
            "Uttar Pradesh",
            "Kannauj",
            "188",
            "34",
            "2"
        ],
        [
            "Uttar Pradesh",
            "Kanpur Dehat",
            "217",
            "35",
            "6"
        ],
        [
            "Uttar Pradesh",
            "Kanpur Nagar",
            "391",
            "43",
            "5"
        ],
        [
            "Uttar Pradesh",
            "Kaushambi",
            "170",
            "37",
            "2"
        ],
        [
            "Uttar Pradesh",
            "Kheri",
            "387",
            "70",
            "7"
        ],
        [
            "Uttar Pradesh",
            "Kushinagar\/Padrauna",
            "339",
            "62",
            "7"
        ],
        [
            "Uttar Pradesh",
            "Lalitpur",
            "191",
            "29",
            "3"
        ],
        [
            "Uttar Pradesh",
            "Lucknow",
            "336",
            "35",
            "9"
        ],
        [
            "Uttar Pradesh",
            "Maharganj",
            "278",
            "54",
            "5"
        ],
        [
            "Uttar Pradesh",
            "Mahoba",
            "140",
            "22",
            "4"
        ],
        [
            "Uttar Pradesh",
            "Mainpuri",
            "203",
            "51",
            "3"
        ],
        [
            "Uttar Pradesh",
            "Mathura",
            "261",
            "43",
            "6"
        ],
        [
            "Uttar Pradesh",
            "Mau",
            "225",
            "48",
            "5"
        ],
        [
            "Uttar Pradesh",
            "Meerut",
            "358",
            "43",
            "3"
        ],
        [
            "Uttar Pradesh",
            "Mirzapur",
            "265",
            "49",
            "7"
        ],
        [
            "Uttar Pradesh",
            "Moradabad",
            "416",
            "55",
            "5"
        ],
        [
            "Uttar Pradesh",
            "Muzzafarnagar",
            "417",
            "73",
            "7"
        ],
        [
            "Uttar Pradesh",
            "Pilibhit",
            "195",
            "33",
            "5"
        ],
        [
            "Uttar Pradesh",
            "Pratapgarh",
            "360",
            "71",
            "11"
        ],
        [
            "Uttar Pradesh",
            "Rae Bareli",
            "377",
            "72",
            "4"
        ],
        [
            "Uttar Pradesh",
            "Rampur",
            "211",
            "36",
            "5"
        ],
        [
            "Uttar Pradesh",
            "Saharanpur",
            "338",
            "53",
            "6"
        ],
        [
            "Uttar Pradesh",
            "Sant Kabir Nagar",
            "182",
            "28",
            "2"
        ],
        [
            "Uttar Pradesh",
            "Sant Ravidas Nagar\/ Bhadohi",
            "155",
            "28",
            "3"
        ],
        [
            "Uttar Pradesh",
            "Shahjahanpur",
            "310",
            "53",
            "4"
        ],
        [
            "Uttar Pradesh",
            "Shravasti",
            "167",
            "24",
            "4"
        ],
        [
            "Uttar Pradesh",
            "Siddharthnagar",
            "274",
            "81",
            "7"
        ],
        [
            "Uttar Pradesh",
            "Sitapur",
            "448",
            "83",
            "9"
        ],
        [
            "Uttar Pradesh",
            "Sonbhadra",
            "165",
            "33",
            "4"
        ],
        [
            "Uttar Pradesh",
            "Sultanpur",
            "403",
            "79",
            "12"
        ],
        [
            "Uttar Pradesh",
            "Unnao",
            "348",
            "56",
            "5"
        ],
        [
            "Uttar Pradesh",
            "Varanasi",
            "312",
            "42",
            "5"
        ],
        [
            "Uttar Pradesh",
            "Total",
            "20521",
            "3640",
            "372"
        ],
        [
            "Uttaranchal",
            "Almora",
            "191",
            "25",
            "4"
        ],
        [
            "Uttaranchal",
            "Bageshwar",
            "64",
            "10",
            "2"
        ],
        [
            "Uttaranchal",
            "Chamoli",
            "96",
            "7",
            "5"
        ],
        [
            "Uttaranchal",
            "Champawat",
            "57",
            "5",
            "2"
        ],
        [
            "Uttaranchal",
            "Dehradun",
            "153",
            "21",
            "6"
        ],
        [
            "Uttaranchal",
            " Pauri Garhwal",
            "203",
            "26",
            "5"
        ],
        [
            "Uttaranchal",
            "Haridwar",
            "143",
            "24",
            "3"
        ],
        [
            "Uttaranchal",
            "Nainital",
            "132",
            "18",
            "4"
        ],
        [
            "Uttaranchal",
            "Pithoragarh",
            "146",
            "18",
            "4"
        ],
        [
            "Uttaranchal",
            "Rudraprayag",
            "62",
            "8",
            "2"
        ],
        [
            "Uttaranchal",
            "Tehri Garhwal",
            "157",
            "23",
            "4"
        ],
        [
            "Uttaranchal",
            "Udhamsingh Nagar",
            "152",
            "26",
            "6"
        ],
        [
            "Uttaranchal",
            "Uttarkashi",
            "75",
            "11",
            "2"
        ],
        [
            "Uttaranchal",
            "Total",
            "1631",
            "222",
            "49"
        ],
        [
            "West Bengal",
            "Bankura ",
            "564",
            "70",
            "22"
        ],
        [
            "West Bengal",
            "Barddhaman ",
            "765",
            "103",
            "35"
        ],
        [
            "West Bengal",
            "Birbhum",
            "484",
            "58",
            "19"
        ],
        [
            "West Bengal",
            "Dakshin Dinajpur",
            "247",
            "19",
            "7"
        ],
        [
            "West Bengal",
            "Darjiling ",
            "230",
            "21",
            "11"
        ],
        [
            "West Bengal",
            "Haora ",
            "448",
            "41",
            "15"
        ],
        [
            "West Bengal",
            "Hugli ",
            "660",
            "60",
            "17"
        ],
        [
            "West Bengal",
            "Jalpaiguri ",
            "537",
            "38",
            "14"
        ],
        [
            "West Bengal",
            "Koch Bihar ",
            "406",
            "29",
            "12"
        ],
        [
            "West Bengal",
            "Kolkata",
            "0",
            "0",
            "0"
        ],
        [
            "West Bengal",
            "Maldah ",
            "511",
            "35",
            "16"
        ],
        [
            "West Bengal",
            "Medinipur(W)",
            "858",
            "84",
            "29"
        ],
        [
            "West Bengal",
            "Medinipur(E)",
            "706",
            "54",
            "25"
        ],
        [
            "West Bengal",
            "Murshidabad ",
            "832",
            "70",
            "27"
        ],
        [
            "West Bengal",
            "Nadia ",
            "469",
            "49",
            "17"
        ],
        [
            "West Bengal",
            "North Twenty Four Parganas",
            "742",
            "53",
            "22"
        ],
        [
            "West Bengal",
            "Puruliya",
            "485",
            "53",
            "20"
        ],
        [
            "West Bengal",
            "South  Twenty Four Parganas",
            "1068",
            "63",
            "30"
        ],
        [
            "West Bengal",
            "Uttar Dinajpur",
            "344",
            "22",
            "8"
        ]
    ]
}